{
  "rest": {
    "categories": [
      {
        "key": "bedroom-furniture",
        "typeId": "category"
      },
      {
        "key": "furniture",
        "typeId": "category"
      },
      {
        "key": "beds",
        "typeId": "category"
      }
    ],
    "masterVariant": {
      "sku": "MTB-023",
      "prices": [
        {
          "value": {
            "centAmount": 129900,
            "currencyCode": "EUR"
          },
          "country": "DE"
        },
        {
          "value": {
            "centAmount": 129900,
            "currencyCode": "GBP"
          },
          "country": "GB"
        },
        {
          "value": {
            "centAmount": 129900,
            "currencyCode": "USD"
          },
          "country": "US"
        }
      ],
      "images": [
        {
          "url": "https://2eca75039cf911b9bbe5-79bfd3e36f011d786971804e873c4354.ssl.cf3.rackcdn.com/Opal%20King%20Bed%20(1)-ijN8T8rE.jpeg",
          "dimensions": {
            "w": 2000,
            "h": 2000
          }
        }
      ],
      "attributes": [
        {
          "name": "productspec",
          "value": {
            "en-GB": "- Assembly included",
            "de-DE": "- Montage inklusive",
            "en-US": "- Assembly included"
          }
        },
        {
          "name": "product-description",
          "value": {
            "en-GB": "A modern king bed with a tufted headboard is a stylish and elegant piece of furniture that can bring a touch of luxury and sophistication to any bedroom. The mattress platform is large enough to accommodate a king-size mattress, and the entire bed is designed with clean, sleek lines that give it a modern look.  The tufted headboard is the centerpiece of the bed and is often the most eye-catching feature. It is made of soft, durable fabric that is tufted in a square pattern. The tufted design gives the headboard a plush, cushioned appearance, making it comfortable for sitting up in bed to read or watch TV.  The overall design of the bed is modern, emphasizing the beauty of the tufted headboard.   Overall, a modern king bed with a tufted headboard is a statement piece that can add both style and comfort to any bedroom.",
            "en-US": "A modern king bed with a tufted headboard is a stylish and elegant piece of furniture that can bring a touch of luxury and sophistication to any bedroom. The mattress platform is large enough to accommodate a king-size mattress, and the entire bed is designed with clean, sleek lines that give it a modern look.  The tufted headboard is the centerpiece of the bed and is often the most eye-catching feature. It is made of soft, durable fabric that is tufted in a square pattern. The tufted design gives the headboard a plush, cushioned appearance, making it comfortable for sitting up in bed to read or watch TV.  The overall design of the bed is modern, emphasizing the beauty of the tufted headboard.   Overall, a modern king bed with a tufted headboard is a statement piece that can add both style and comfort to any bedroom.",
            "de-DE": "Ein modernes Kingsize-Bett mit getuftetem Kopfteil ist ein stilvolles und elegantes Möbelstück, das jedem Schlafzimmer einen Hauch von Luxus und Raffinesse verleihen kann. Die Matratzenplattform ist groß genug, um eine Kingsize-Matratze aufzunehmen, und das gesamte Bett ist mit klaren, schlanken Linien gestaltet, die ihm ein modernes Aussehen verleihen.  Das getuftete Kopfteil ist das Herzstück des Bettes und oft der auffälligste Blickfang. Es besteht aus weichem, strapazierfähigem Stoff, der in einem quadratischen Muster getuftet ist. Das getuftete Design verleiht dem Kopfteil ein weiches, gepolstertes Aussehen und macht es bequem, im Bett zu sitzen, um zu lesen oder fernzusehen.  Das Gesamtdesign des Bettes ist modern und betont die Schönheit des getufteten Kopfteils.  Insgesamt ist ein modernes Kingsize-Bett mit getuftetem Kopfteil ein Statement-Stück, das jedem Schlafzimmer sowohl Stil als auch Komfort verleihen kann."
          }
        },
        {
          "name": "color",
          "value": {
            "en-GB": "#000",
            "de-DE": "#000",
            "en-US": "#000"
          }
        },
        {
          "name": "colorlabel",
          "value": {
            "en-GB": "Black",
            "de-DE": "Schwarz",
            "en-US": "Black"
          }
        },
        {
          "name": "color-filter",
          "value": {
            "key": "#000",
            "label": {
              "de-DE": "Schwarz",
              "en-GB": "Black",
              "en-US": "Black"
            }
          }
        }
      ]
    },
    "name": {
      "de-DE": "Opal Kingsize-Bett",
      "en-GB": "Opal King Bed",
      "en-US": "Opal King Bed"
    },
    "productType": {
      "key": "furniture-and-decor",
      "typeId": "product-type"
    },
    "slug": {
      "de-DE": "opal-kingsize-bett",
      "en-GB": "opal-king-bed",
      "en-US": "opal-king-bed"
    }
  }
}